[
    { "id": "Anderson Hall", "label": "Anderson Hall" },
    { "id": "Art Building", "label": "Art Building" },
    { "id": "Bagley Hall", "label": "Bagley Hall" },
    { "id": "Balmer Hall", "label": "Balmer Hall" },
    { "id": "Bank of America Executive Education Center", "label": "Bank of America Executive Education Center" },
    { "id": "Benson Hall", "label": "Benson Hall" },
    { "id": "Bloedel Hall", "label": "Bloedel Hall" },
    { "id": "Burke Museum", "label": "Burke Museum" },
    { "id": "By George Cafe", "label": "By George Cafe" },
    { "id": "Campus Police Building", "label": "Campus Police Building" },
    { "id": "Condon Hall", "label": "Condon Hall" },
    { "id": "Dempsey Hall", "label": "Dempsey Hall" },
    { "id": "Denny Hall", "label": "Denny Hall" },
    { "id": "Fisheries Sciences Building", "label": "Fisheries Sciences Building" },
    { "id": "Foege Building", "label": "Foege Building" },
    { "id": "Gerberding Hall", "label": "Gerberding Hall" },
    { "id": "Gould Hall", "label": "Gould Hall" },
    { "id": "Guggenheim Hall", "label": "Guggenheim Hall" },
    { "id": "Haggett Hall", "label": "Haggett Hall" },
    { "id": "Hansee Hall", "label": "Hansee Hall" },
    { "id": "Health Sciences Building", "label": "Health Sciences Building" },
    { "id": "Henry Art Gallery", "label": "Henry Art Gallery" },
    { "id": "HUB (Husky Union Building)", "label": "HUB (Husky Union Building)" },
    { "id": "Hutchinson Hall", "label": "Hutchinson Hall" },
    { "id": "Kane Hall", "label": "Kane Hall" },
    { "id": "Loew Hall", "label": "Loew Hall" },
    { "id": "Mary Gates Hall", "label": "Mary Gates Hall" },
    { "id": "McCarty Hall", "label": "McCarty Hall" },
    { "id": "McMahon Hall", "label": "McMahon Hall" },
    { "id": "Meany Hall", "label": "Meany Hall" },
    { "id": "Miller Hall", "label": "Miller Hall" },
    { "id": "Molecular Engineering & Sciences Building", "label": "Molecular Engineering & Sciences Building" },
    { "id": "More Hall", "label": "More Hall" },
    { "id": "Padelford Hall", "label": "Padelford Hall" },
    { "id": "Parrington Hall", "label": "Parrington Hall" },
    { "id": "Paul G. Allen Center for Computer Science & Engineering", "label": "Paul G. Allen Center for Computer Science & Engineering" },
    { "id": "Physics/Astronomy Building", "label": "Physics/Astronomy Building" },
    { "id": "Raitt Hall", "label": "Raitt Hall" },
    { "id": "Savery Hall", "label": "Savery Hall" },
    { "id": "Schmitz Hall", "label": "Schmitz Hall" },
    { "id": "William H. Foege Bioengineering Building", "label": "William H. Foege Bioengineering Building" },
    { "id": "William H. Gates Hall", "label": "William H. Gates Hall" }
  ]
  